docker_run/__init__.py
docker_run/__main__.py
docker_run/core.py
docker_run/utils.py
docker_run/bash_completion.d/docker-run
docker_run/plugins/__init__.py
docker_run/plugins/core.py
docker_run/plugins/plugin.py
docker_run_cli-0.10.2.data/scripts/activate-python-docker-run-shell-completion
docker_run_cli-0.10.2.data/scripts/docker-run
docker_run_cli-0.10.2.dist-info/licenses/LICENSE
docker_run_cli-0.10.2.dist-info/METADATA
docker_run_cli-0.10.2.dist-info/WHEEL
docker_run_cli-0.10.2.dist-info/top_level.txt
docker_run_cli-0.10.2.dist-info/RECORD
