Metadata-Version: 2.4
Name: docker-run-cli
Version: 0.10.2
Summary: 'docker run' and 'docker exec' with useful defaults
Author-email: Lennart Reiher <lennart.reiher@rwth-aachen.de>, Jean-Pierre Busch <jean-pierre.busch@rwth-aachen.de>
Maintainer-email: Lennart Reiher <lennart.reiher@rwth-aachen.de>, Jean-Pierre Busch <jean-pierre.busch@rwth-aachen.de>
License: MIT License
Project-URL: Repository, https://github.com/ika-rwth-aachen/docker-run
Project-URL: Bug Tracker, https://github.com/ika-rwth-aachen/docker-run/issues
Keywords: docker,container
Classifier: License :: OSI Approved :: MIT License
Classifier: Programming Language :: Python
Classifier: Programming Language :: Python :: 3
Classifier: Operating System :: POSIX :: Linux
Requires-Python: >=3.7
License-File: LICENSE
Requires-Dist: nvidia-ml-py~=12.570.86
Provides-Extra: dev
Requires-Dist: build; extra == "dev"
Requires-Dist: twine; extra == "dev"
Provides-Extra: docker-ros
Requires-Dist: docker-run-docker-ros>=1.0.9; extra == "docker-ros"
Provides-Extra: plugins
Requires-Dist: docker-run-docker-ros>=1.0.9; extra == "plugins"
Provides-Extra: all
Requires-Dist: docker-run-docker-ros>=1.0.9; extra == "all"
Requires-Dist: build; extra == "all"
Requires-Dist: twine; extra == "all"
Dynamic: license-file
